LICENSE
MANIFEST.in
README.rst
run_tests.py
setup.cfg
setup.py
dbfread/__init__.py
dbfread/codepages.py
dbfread/dbf.py
dbfread/dbversions.py
dbfread/deprecated_dbf.py
dbfread/exceptions.py
dbfread/field_parser.py
dbfread/ifiles.py
dbfread/memo.py
dbfread/struct_parser.py
dbfread/test_field_parser.py
dbfread/test_ifiles.py
dbfread/test_invalid_value.py
dbfread/test_memo.py
dbfread/test_read_and_length.py
dbfread/version.py
docs/Makefile
docs/acknowledgements.rst
docs/api_changes.rst
docs/changes.rst
docs/conf.py
docs/dbf_objects.rst
docs/exporting_data.rst
docs/field_types.rst
docs/index.rst
docs/installing.rst
docs/introduction.rst
docs/license.rst
docs/make.bat
docs/resources.rst
docs/_static/PLACEHOLDER
examples/custom_field_type.py
examples/dbf2sqlite
examples/dbfinfo.py
examples/namedtuples.py
examples/pandas_dataframe.py
examples/print_csv.py
examples/print_invalid_values.py
examples/record_objects.py
examples/using_dataset.py
examples/files/invalid_value.dbf
examples/files/make_example_files.py
examples/files/people.dbf
td_dbfread.egg-info/PKG-INFO
td_dbfread.egg-info/SOURCES.txt
td_dbfread.egg-info/dependency_links.txt
td_dbfread.egg-info/top_level.txt
td_dbfread.egg-info/zip-safe
testcases/memotest.FPT
testcases/memotest.dbf
testcases/no_memofile.dbf