Metadata-Version: 1.1
Name: td-dbfread
Version: 2.0.8
Summary: Read DBF Files with Python
Home-page: https://dbfread.readthedocs.io/
Author: Ole Martin Bjorndalen
Author-email: ombdalen@gmail.com
License: MIT
Platform: UNKNOWN
Classifier: Development Status :: 5 - Production/Stable
Classifier: Intended Audience :: Developers
Classifier: Natural Language :: English
Classifier: License :: OSI Approved :: MIT License
Classifier: Programming Language :: Python
Classifier: Programming Language :: Python :: 2.7
Classifier: Programming Language :: Python :: 3.2
